ttyutility/Command.py
ttyutility/__init__.py
ttyutility/console.py
tty_utility-1.0.0.dist-info/METADATA
tty_utility-1.0.0.dist-info/WHEEL
tty_utility-1.0.0.dist-info/top_level.txt
tty_utility-1.0.0.dist-info/RECORD
